easygdf/__init__.py
easygdf/constants.py
easygdf/easygdf.py
easygdf/exceptions.py
easygdf/initial_distribution.py
easygdf/screens_touts.py
easygdf/utils.py
easygdf/data/initial_distribution.gdf
easygdf/data/screens_touts.gdf
easygdf-2.1.1.dist-info/LICENSE.txt
easygdf-2.1.1.dist-info/METADATA
easygdf-2.1.1.dist-info/WHEEL
easygdf-2.1.1.dist-info/top_level.txt
easygdf-2.1.1.dist-info/RECORD
