Metadata-Version: 2.2
Name: easygdf
Version: 2.1.1
Summary: A python library to make working with GDF files a breeze.
Author-email: "Christopher M. Pierce" <contact@chris-pierce.com>
License: BSD 3-Clause License
Project-URL: Homepage, https://github.com/electronsandstuff/easygdf
Classifier: Programming Language :: Python :: 3
Classifier: Operating System :: OS Independent
Classifier: License :: OSI Approved :: BSD License
Requires-Python: >=3.9
License-File: LICENSE.txt
Requires-Dist: numpy
